spakky/core/__init__.py
spakky/core/aop/__init__.py
spakky/core/aop/advisor.py
spakky/core/aop/aspect.py
spakky/core/aop/error.py
spakky/core/aop/interfaces/__init__.py
spakky/core/aop/interfaces/aspect.py
spakky/core/aop/pointcut.py
spakky/core/aop/post_processor.py
spakky/core/application/__init__.py
spakky/core/application/application.py
spakky/core/application/application_context.py
spakky/core/application/error.py
spakky/core/application/plugin.py
spakky/core/aspects/__init__.py
spakky/core/aspects/logging.py
spakky/core/common/__init__.py
spakky/core/common/annotation.py
spakky/core/common/constants.py
spakky/core/common/error.py
spakky/core/common/importing.py
spakky/core/common/interfaces/__init__.py
spakky/core/common/interfaces/cloneable.py
spakky/core/common/interfaces/comparable.py
spakky/core/common/interfaces/disposable.py
spakky/core/common/interfaces/equatable.py
spakky/core/common/interfaces/representable.py
spakky/core/common/metadata.py
spakky/core/common/mro.py
spakky/core/common/mutability.py
spakky/core/common/proxy.py
spakky/core/common/types.py
spakky/core/pod/__init__.py
spakky/core/pod/annotations/__init__.py
spakky/core/pod/annotations/lazy.py
spakky/core/pod/annotations/order.py
spakky/core/pod/annotations/pod.py
spakky/core/pod/annotations/primary.py
spakky/core/pod/annotations/qualifier.py
spakky/core/pod/error.py
spakky/core/pod/inject.py
spakky/core/pod/interfaces/__init__.py
spakky/core/pod/interfaces/application_context.py
spakky/core/pod/interfaces/aware/__init__.py
spakky/core/pod/interfaces/aware/application_context_aware.py
spakky/core/pod/interfaces/aware/aware.py
spakky/core/pod/interfaces/aware/container_aware.py
spakky/core/pod/interfaces/container.py
spakky/core/pod/interfaces/post_processor.py
spakky/core/pod/post_processors/__init__.py
spakky/core/pod/post_processors/aware_post_processor.py
spakky/core/py.typed
spakky/core/service/__init__.py
spakky/core/service/background.py
spakky/core/service/interfaces/__init__.py
spakky-5.0.1.dist-info/WHEEL
spakky-5.0.1.dist-info/METADATA
spakky-5.0.1.dist-info/RECORD
