Metadata-Version: 2.3
Name: spakky
Version: 5.0.1
Summary: Core module for Spakky framework to support DI/IoC, AOP, Plugin system, and more.
Author: Spakky
Author-email: Spakky <sejong418@icloud.com>
License: MIT
Requires-Dist: spakky-fastapi>=5.0.1 ; extra == 'fastapi'
Requires-Dist: spakky-kafka>=5.0.1 ; extra == 'kafka'
Requires-Dist: spakky-rabbitmq>=5.0.1 ; extra == 'rabbitmq'
Requires-Dist: spakky-security>=5.0.1 ; extra == 'security'
Requires-Dist: spakky-typer>=5.0.1 ; extra == 'typer'
Requires-Python: >=3.11
Provides-Extra: fastapi
Provides-Extra: kafka
Provides-Extra: rabbitmq
Provides-Extra: security
Provides-Extra: typer
